[
  {
    "placa": "T6F869",
    "familia": "F",
    "picador": "FRANCIA MENA, LIZANDRO",
    "nombre": "FRANCIA MENA, LIZANDRO",
    "controlador": "0",
    "kg": 100.28,
    "kg_regular": 100.28,
    "zona": "A",
    "material": "1004551",
    "denominacion": "GLORIA CREMA DE LECHE UHTX200ML TTSX24UN",
    "cajas": 18,
    "unds": 229,
    "n_orden": 0,
    "timestamp": "2026-07-10T05:32:59.686Z"
  },
  {
    "placa": "T6F869",
    "familia": "B",
    "picador": "ZAPATA OYARCE MARCO ANTONIO",
    "nombre": "ZAPATA OYARCE MARCO ANTONIO",
    "controlador": "0",
    "kg": 404.93,
    "kg_regular": 135.65,
    "zona": "A",
    "material": "3759",
    "denominacion": "GLORIA LECHE CONDENSADA PD 200GR DOYPACK",
    "cajas": 26,
    "unds": 251,
    "n_orden": 0,
    "timestamp": "2026-07-10T05:33:47.220Z"
  },
  {
    "placa": "T6F869",
    "familia": "G",
    "picador": "ZAPATA OYARCE MARCO ANTONIO",
    "nombre": "ZAPATA OYARCE MARCO ANTONIO",
    "controlador": "0",
    "kg": 7.26,
    "kg_regular": 7.26,
    "zona": "A",
    "material": "1033001",
    "denominacion": "PRO POWER UHT 320 ML DARK CHOCOLATE X6",
    "cajas": 3,
    "unds": 2,
    "n_orden": 0,
    "timestamp": "2026-07-10T05:33:48.717Z"
  }
]