{
  "ultima_actualizacion": "16/07/2026 22:58:35",
  "dias": {
    "2026-06-01": {
      "por_familia": {
        "B": 18197.74,
        "A": 23513.21,
        "C": 17527.2,
        "F": 6850.83,
        "G": 240.28,
        "E": 6593.06,
        "D": 3378.63
      },
      "por_status": {
        "A": 34944.49,
        "B": 14009.32,
        "C": 20717.84,
        "PEN": 6629.3
      },
      "por_placa": {
        "W6L701": 1210.32,
        "D3L703": 1337.87,
        "A5K897": 1892.85,
        "AXB855": 1299.1,
        "A1Q874": 1657.62,
        "D9G880": 1327.36,
        "AMQ791": 1894.76,
        "ATB831": 1026.34,
        "AUP711": 2382.04,
        "ARD784": 1177.27,
        "F3M892": 1612.4,
        "D0I718": 2180.85,
        "AXH708": 1354.61,
        "C5G823": 2870.53,
        "ATP870": 1352.54,
        "B0V924": 1285.55,
        "F7X829": 1207.57,
        "D7L941": 2460.87,
        "A6R946": 2146.78,
        "AMF737": 1570.14,
        "F7B746": 1305.98,
        "T6F869": 2452.59,
        "C5R934": 1026.85,
        "C1J747": 2578.12,
        "F9W785": 1067.75,
        "A7Y808": 1174.78,
        "A4G840": 1365.27,
        "C2B801": 1463.04,
        "ARZ862": 1088.62,
        "A6P899": 2009.75,
        "D2H719": 1139.68,
        "APU790": 2186.82,
        "A5Y854": 2606.57,
        "ASM812": 1017.98,
        "BKV855": 1228.22,
        "C3Q769": 1102.85,
        "ASM907": 1030.72,
        "V2F841": 1816.41,
        "D1V932": 2171.43,
        "APC840": 1028.17,
        "P4A742": 2503.53,
        "CKI862": 1146.03,
        "F1E927": 2146.1,
        "BBI909": 1707.21,
        "AWH909": 1135.62,
        "APB825": 1213.81,
        "AHX902": 1227.71,
        "ASA790": 1111.97
      },
      "por_almacen": {
        "ABARROTES": 62869.91,
        "REFRIGERADOS": 13431.04
      },
      "por_estado": {
        "Picking_Regular": 56698.67,
        "Picking Directo": 19602.28
      },
      "total_kg": 76300.95,
      "total_registros": 4733
    },
    "2026-06-02": {
      "por_familia": {
        "B": 25846.6,
        "C": 27002.45,
        "A": 26591.43,
        "F": 10026.09,
        "G": 436.3,
        "E": 8849.95,
        "D": 5546.52
      },
      "por_status": {
        "A": 42806.63,
        "C": 30664.07,
        "B": 25316.65,
        "PEN": 5512.0
      },
      "por_placa": {
        "ASM812": 1488.7,
        "D3L703": 1796.07,
        "C1J747": 1154.3,
        "ATP870": 1239.96,
        "A4G840": 2003.71,
        "APC840": 1681.55,
        "AMQ791": 2493.7,
        "F7X829": 1904.23,
        "C3Q769": 920.12,
        "ACX716": 2225.71,
        "A5Y854": 1881.12,
        "AMF737": 4243.17,
        "T6F869": 1581.68,
        "ATB831": 3010.19,
        "D7L941": 2526.81,
        "D9G880": 3188.57,
        "APU790": 1802.78,
        "A6R946": 2419.98,
        "F7B746": 1767.21,
        "P4A742": 2481.9,
        "F9W785": 1492.31,
        "APB825": 2163.19,
        "D0I718": 1010.65,
        "V2F841": 3321.96,
        "ASA790": 2282.57,
        "CKI862": 1309.25,
        "A1Q874": 1373.11,
        "AWH909": 2288.33,
        "A5K897": 1852.8,
        "ARZ862": 2752.13,
        "D1V932": 1484.57,
        "ARD784": 1666.33,
        "AUP711": 3994.42,
        "AXH708": 3175.63,
        "A6P899": 1442.82,
        "A7Y808": 1525.15,
        "AXB855": 1704.88,
        "B0V924": 1406.64,
        "BBI909": 2144.0,
        "C5G823": 3402.29,
        "AHX902": 2441.83,
        "D4R705": 2371.89,
        "AWC785": 1810.82,
        "C8F736": 2410.47,
        "ASM907": 1809.0,
        "BKV855": 2673.77,
        "W6L701": 1304.23,
        "C5R934": 1636.85,
        "F1E927": 1065.69,
        "C2B801": 3170.29
      },
      "por_almacen": {
        "ABARROTES": 85464.44,
        "REFRIGERADOS": 18834.9
      },
      "por_estado": {
        "Picking_Regular": 75797.3,
        "Picking Directo": 28502.04
      },
      "total_kg": 104299.35,
      "total_registros": 5528
    },
    "2026-07-02": {
      "por_familia": {
        "B": 26583.71,
        "A": 30128.86,
        "C": 23620.38,
        "F": 9532.15,
        "G": 407.91,
        "E": 10095.05,
        "D": 3613.91
      },
      "por_status": {
        "A": 20879.22,
        "D": 22501.96,
        "P": 16977.19,
        "C": 22524.48,
        "B": 21099.14
      },
      "por_placa": {
        "B0V924": 2445.48,
        "AHX902": 2602.43,
        "D0I718": 1430.95,
        "ARZ862": 1137.08,
        "ASM907": 1980.55,
        "AUP711": 1813.85,
        "C1J747": 1830.24,
        "D1V932": 1714.83,
        "AWH909": 2490.67,
        "APB825": 2194.25,
        "ATP870": 2043.59,
        "AMF737": 1828.34,
        "ATB831": 1321.45,
        "D4R705": 2066.75,
        "F7X829": 2202.65,
        "W6L701": 1921.57,
        "A6P899": 2403.41,
        "T6F869": 1835.86,
        "A6R946": 2400.65,
        "BKV855": 1614.3,
        "D2H719": 2007.86,
        "ASM812": 1039.5,
        "A7Y808": 2992.5,
        "AXB855": 1458.21,
        "ASA790": 1242.74,
        "C5G823": 2131.65,
        "ACX716": 1887.03,
        "D3L703": 2255.83,
        "CKI862": 2407.07,
        "D7L941": 3063.69,
        "APC840": 2074.57,
        "F7B746": 1936.91,
        "A5K897": 2553.43,
        "D9G880": 3409.56,
        "ARD784": 1912.93,
        "F1E927": 1958.14,
        "V2F841": 2765.22,
        "ANI940": 2013.26,
        "APU790": 1311.86,
        "AMQ791": 2043.12,
        "A4G840": 1970.45,
        "AWC785": 1349.29,
        "C3Q769": 1463.82,
        "C8F736": 1311.71,
        "C5R934": 1262.49,
        "A1Q874": 1331.06,
        "A5Y854": 2225.46,
        "C2B801": 2582.82,
        "F3M892": 1190.47,
        "P4A742": 2576.84,
        "AXH708": 2143.08,
        "F9W785": 2830.52
      },
      "por_almacen": {
        "ABARROTES": 84389.06,
        "REFRIGERADOS": 19592.93
      },
      "por_estado": {
        "Picking_Regular": 74666.41,
        "Picking Directo": 29315.57
      },
      "total_kg": 103981.99,
      "total_registros": 5608
    },
    "2026-06-03": {
      "por_familia": {
        "B": 27770.37,
        "A": 31867.32,
        "C": 21883.07,
        "F": 10108.66,
        "G": 509.75,
        "E": 9807.78,
        "D": 4726.62
      },
      "por_status": {
        "B": 23630.63,
        "A": 43980.88,
        "C": 36809.8,
        "PEN": 2252.26
      },
      "por_placa": {
        "T6F869": 2174.55,
        "D0I718": 1576.96,
        "ASM907": 1831.12,
        "AXH708": 1486.87,
        "A1Q874": 2780.65,
        "W6L701": 1343.5,
        "D7L941": 2182.46,
        "F7X829": 2618.68,
        "APB825": 1876.95,
        "C8F736": 1666.3,
        "AMF737": 1717.47,
        "F7B746": 1623.94,
        "AMQ791": 1910.15,
        "CKI862": 2769.53,
        "C5G823": 1946.06,
        "ARZ862": 1939.91,
        "A7Y808": 2295.68,
        "F9W785": 1253.12,
        "D3L703": 2820.44,
        "C5R934": 3797.72,
        "C2B801": 2129.81,
        "APU790": 3352.98,
        "D2H719": 1451.77,
        "ACX716": 1390.04,
        "C3Q769": 1784.19,
        "D4R705": 3364.19,
        "BKV855": 2412.54,
        "A5Y854": 1837.59,
        "F1E927": 1366.28,
        "A5K897": 1950.62,
        "ATP870": 2348.03,
        "A6P899": 1969.3,
        "AXB855": 1693.35,
        "V2F841": 2130.84,
        "ASM812": 2139.21,
        "C1J747": 1601.76,
        "A6R946": 2856.06,
        "F3M892": 3042.65,
        "APC840": 2641.79,
        "A4G840": 2749.1,
        "P4A742": 2252.26,
        "ASA790": 1476.71,
        "AWH909": 4338.11,
        "D9G880": 1733.61,
        "ATB831": 2447.91,
        "ARD784": 3096.55,
        "AHX902": 2606.16,
        "AUP711": 2898.1
      },
      "por_almacen": {
        "ABARROTES": 86775.98,
        "REFRIGERADOS": 19897.59
      },
      "por_estado": {
        "Picking_Regular": 76579.69,
        "Picking Directo": 30093.89
      },
      "total_kg": 106673.57,
      "total_registros": 5370
    },
    "2026-07-03": {
      "por_familia": {
        "B": 26257.81,
        "A": 53881.42,
        "C": 22244.79,
        "F": 7934.18,
        "G": 515.61,
        "E": 8846.15,
        "D": 4329.89
      },
      "por_status": {
        "P": 22307.93,
        "B": 21480.21,
        "C": 21649.87,
        "A": 23862.35,
        "D": 34709.47
      },
      "por_placa": {
        "C3Q769": 2246.21,
        "A5Y854": 1705.97,
        "A6R946": 3434.69,
        "C1J747": 1347.25,
        "AXH708": 1477.99,
        "ACX716": 1748.65,
        "CKI862": 1932.52,
        "D4R705": 2477.05,
        "D9G880": 2799.65,
        "AWH909": 3642.4,
        "ASM812": 1896.35,
        "A5K897": 2750.56,
        "AUP711": 2488.25,
        "A6P899": 2773.82,
        "A4G840": 1747.12,
        "APU790": 2903.65,
        "ATP870": 1617.61,
        "T6F869": 1519.51,
        "C5R934": 2041.75,
        "A7Y808": 2275.34,
        "ASA790": 2383.3,
        "F1E927": 1513.39,
        "D1V932": 1913.2,
        "ASM907": 1451.54,
        "ATB831": 2680.61,
        "AHX902": 2671.56,
        "APC840": 2081.52,
        "D7L941": 2221.76,
        "W6L701": 1742.95,
        "D2H719": 3161.98,
        "B0V924": 1468.18,
        "F3M892": 2466.86,
        "ARZ862": 2572.23,
        "F9W785": 1397.93,
        "C8F736": 2711.53,
        "BKV855": 1923.35,
        "P4A742": 2267.99,
        "V2F841": 3604.44,
        "AMQ791": 1512.72,
        "ARD784": 1776.02,
        "D3L703": 1642.07,
        "AMF737": 1904.39,
        "A1Q874": 1068.38,
        "F7B746": 2377.81,
        "D0I718": 2268.1,
        "APB825": 2651.3,
        "AVA931": 3705.56,
        "BBI909": 2683.52,
        "C2B801": 3528.4,
        "F3V817": 2908.27,
        "F7X829": 2219.68,
        "ANI940": 1730.88,
        "AXB855": 1709.63,
        "AWC785": 1736.09,
        "C5G823": 3526.34
      },
      "por_almacen": {
        "ABARROTES": 107229.51,
        "REFRIGERADOS": 16780.32
      },
      "por_estado": {
        "Picking_Regular": 79970.68,
        "Picking Directo": 44039.15
      },
      "total_kg": 124009.83,
      "total_registros": 5593
    },
    "2026-06-04": {
      "por_familia": {
        "A": 27777.8,
        "B": 26483.24,
        "C": 17811.6,
        "F": 8785.23,
        "G": 413.43,
        "E": 10678.99,
        "D": 3560.65
      },
      "por_status": {
        "C": 32135.71,
        "A": 37738.37,
        "B": 21444.88,
        "PEN": 4191.98
      },
      "por_placa": {
        "ASM907": 2011.41,
        "W6L701": 1525.94,
        "AXH708": 3113.51,
        "ATP870": 1778.1,
        "F7X829": 2238.31,
        "ARZ862": 1930.3,
        "C5G823": 2625.76,
        "BBI909": 2923.13,
        "T6F869": 2185.68,
        "AWC785": 2091.16,
        "F7B746": 1659.02,
        "C8F736": 1801.3,
        "F3M892": 1946.88,
        "AUP711": 1316.17,
        "C5R934": 1416.2,
        "F9W785": 2441.97,
        "AHX902": 2531.2,
        "AMF737": 2100.82,
        "AMQ791": 2071.68,
        "B0V924": 1945.59,
        "BKV855": 1208.94,
        "D2H719": 1942.43,
        "A6R946": 1233.36,
        "D4R705": 1543.8,
        "APU790": 1148.13,
        "C2B801": 2319.96,
        "ASM812": 1521.96,
        "A5Y854": 1774.42,
        "ACX716": 1742.76,
        "D9G880": 3155.66,
        "F1E927": 1396.37,
        "V2F841": 2997.96,
        "A1Q874": 1188.46,
        "D3L703": 3306.3,
        "C1J747": 1933.89,
        "CKI862": 1780.59,
        "D1V932": 1589.35,
        "A6P899": 1945.22,
        "D7L941": 2154.66,
        "A7Y808": 2306.34,
        "C3Q769": 1782.81,
        "AXB855": 1577.15,
        "ARD784": 2438.7,
        "APB825": 2961.29,
        "AWH909": 2411.96,
        "APC840": 1081.65,
        "ASA790": 1201.26,
        "ATB831": 2211.4
      },
      "por_almacen": {
        "ABARROTES": 76057.01,
        "REFRIGERADOS": 19453.94
      },
      "por_estado": {
        "Picking_Regular": 67288.27,
        "Picking Directo": 28222.67
      },
      "total_kg": 95510.94,
      "total_registros": 5342
    },
    "2026-07-04": {
      "por_familia": {
        "B": 28182.0,
        "C": 24731.96,
        "A": 55749.0,
        "F": 7566.78,
        "G": 489.76,
        "D": 3589.76,
        "E": 9337.71
      },
      "por_status": {
        "A": 23238.8,
        "D": 43617.17,
        "B": 22656.54,
        "C": 25884.76,
        "P": 14249.68
      },
      "por_placa": {
        "F1E927": 2831.06,
        "APU790": 1587.46,
        "ASM907": 2236.92,
        "A6P899": 2394.09,
        "AXB855": 2685.2,
        "BBI909": 1622.66,
        "A7Y808": 1857.73,
        "W6L701": 2411.88,
        "A5Y854": 1803.38,
        "D3L703": 1128.91,
        "AUP711": 2802.92,
        "A5K897": 1299.52,
        "AHX902": 1954.13,
        "B0V924": 3805.3,
        "ANI940": 2183.56,
        "ATP870": 2374.98,
        "ARD784": 2476.52,
        "CKI862": 1510.95,
        "D7L941": 3637.03,
        "F3M892": 2703.13,
        "APC840": 3707.58,
        "A1Q874": 1555.77,
        "T6F869": 1523.36,
        "C3Q769": 2891.16,
        "AWC785": 1705.46,
        "A4G840": 2227.17,
        "P4A742": 3124.63,
        "AXH708": 2464.42,
        "F7B746": 2544.44,
        "ASA790": 2852.58,
        "V2F841": 1817.55,
        "D1V932": 2416.62,
        "C1J747": 2514.01,
        "F7X829": 2688.78,
        "C8F736": 1970.3,
        "C2B801": 3391.22,
        "D4R705": 3703.32,
        "C5G823": 2055.4,
        "C5R934": 2452.44,
        "AMF737": 2634.08,
        "D2H719": 2913.72,
        "BKV855": 2460.55,
        "APB825": 2715.95,
        "F9W785": 2814.36,
        "D0I718": 1473.94,
        "ASM812": 2117.64,
        "ATB831": 2239.1,
        "ARZ862": 1611.95,
        "AMQ791": 1516.94,
        "ACX716": 2270.57,
        "A6R946": 2206.78,
        "D9G880": 3110.8,
        "AWH909": 3321.59,
        "F3V817": 3325.43
      },
      "por_almacen": {
        "ABARROTES": 112742.46,
        "REFRIGERADOS": 16904.49
      },
      "por_estado": {
        "Picking_Regular": 77996.8,
        "Picking Directo": 51650.15
      },
      "total_kg": 129646.96,
      "total_registros": 5236
    },
    "2026-06-05": {
      "por_familia": {
        "B": 23908.35,
        "C": 13184.42,
        "F": 7931.42,
        "G": 384.5,
        "E": 8463.63,
        "A": 69297.96,
        "D": 5542.74
      },
      "por_status": {
        "A": 47451.31,
        "PEN": 14923.88,
        "C": 35871.02,
        "B": 30466.81
      },
      "por_placa": {
        "AXB855": 1525.01,
        "AMQ791": 1454.16,
        "A7Y808": 2252.72,
        "CKI862": 1438.87,
        "ASM907": 1093.25,
        "A1Q874": 2274.12,
        "F3M892": 1996.72,
        "ATP870": 2298.83,
        "AXH708": 3372.39,
        "B0V924": 1161.5,
        "A6R946": 3639.41,
        "F9W785": 2923.78,
        "D7L941": 1980.15,
        "P4A742": 1907.34,
        "D2H719": 3912.04,
        "C8F736": 3003.13,
        "AHX902": 2503.33,
        "C2B801": 2752.78,
        "A4G840": 2137.37,
        "ARZ862": 1716.72,
        "F7B746": 2449.81,
        "F1E927": 1777.0,
        "A5Y854": 2537.85,
        "APU790": 2915.76,
        "AMF737": 2783.55,
        "BKV855": 2532.55,
        "ARD784": 1241.17,
        "T6F869": 3001.2,
        "D4R705": 1832.58,
        "ATB831": 2186.71,
        "C1J747": 2538.38,
        "D0I718": 1943.29,
        "AWC785": 1612.28,
        "C5G823": 3464.87,
        "ASM812": 1657.56,
        "D1V932": 1970.54,
        "APB825": 3047.53,
        "W6L701": 2190.09,
        "C5R934": 2673.2,
        "V2F841": 5092.62,
        "C3Q769": 6650.85,
        "D9G880": 1715.7,
        "D3L703": 2700.15,
        "A5K897": 2314.46,
        "ASA790": 1370.82,
        "F7X829": 2061.64,
        "AUP711": 3057.33,
        "A6P899": 3719.12,
        "AWH909": 2037.55,
        "APC840": 3158.55,
        "ACX716": 2180.23,
        "BBI909": 2954.48
      },
      "por_almacen": {
        "ABARROTES": 112354.83,
        "REFRIGERADOS": 16358.2
      },
      "por_estado": {
        "Picking_Regular": 69299.52,
        "Picking Directo": 59413.51
      },
      "total_kg": 128713.03,
      "total_registros": 5183
    },
    "2026-06-06": {
      "por_familia": {
        "B": 19841.93,
        "A": 58135.66,
        "C": 19789.81,
        "F": 7128.77,
        "G": 291.84,
        "E": 8187.26,
        "D": 3009.21
      },
      "por_status": {
        "B": 28462.23,
        "A": 44185.04,
        "C": 31504.76,
        "PEN": 12232.44
      },
      "por_placa": {
        "BBI909": 2402.18,
        "W6L701": 1499.19,
        "F1E927": 949.67,
        "D7L941": 1322.48,
        "ASM907": 1370.09,
        "AXH708": 1896.15,
        "A7Y808": 1064.07,
        "D0I718": 2889.48,
        "APU790": 1162.14,
        "AMQ791": 1535.89,
        "F7X829": 2456.6,
        "A1Q874": 1463.08,
        "A5K897": 1696.4,
        "P4A742": 1073.52,
        "F7B746": 1627.07,
        "AHX902": 1558.42,
        "C5R934": 2988.99,
        "D9G880": 2906.77,
        "T6F869": 1922.71,
        "F9W785": 2223.08,
        "A6P899": 3738.53,
        "AXB855": 3582.32,
        "C1J747": 1729.74,
        "ARZ862": 1920.89,
        "AVA931": 4024.71,
        "ACX716": 2570.95,
        "C8F736": 1906.51,
        "D4R705": 2236.04,
        "BKV855": 1730.2,
        "A6R946": 1571.11,
        "AMF737": 1806.82,
        "B0V924": 4405.88,
        "APC840": 1558.08,
        "C2B801": 3592.62,
        "D1V932": 1631.54,
        "A5Y854": 2350.66,
        "AWC785": 1361.51,
        "D3L703": 1161.44,
        "V2F841": 1230.88,
        "ASM812": 1151.33,
        "ATP870": 2098.46,
        "ASA790": 2234.58,
        "APB825": 1683.47,
        "D2H719": 2469.35,
        "A4G840": 1938.54,
        "ATB831": 2073.56,
        "CKI862": 1338.79,
        "F3M892": 3029.7,
        "AWH909": 4638.8,
        "ARD784": 3130.16,
        "AUP711": 3828.44,
        "C3Q769": 6650.85
      },
      "por_almacen": {
        "ABARROTES": 101086.45,
        "REFRIGERADOS": 15298.03
      },
      "por_estado": {
        "Picking_Regular": 65764.84,
        "Picking Directo": 50619.64
      },
      "total_kg": 116384.48,
      "total_registros": 4908
    },
    "2026-07-06": {
      "por_familia": {
        "B": 24761.87,
        "A": 44654.48,
        "C": 22912.0,
        "F": 6693.41,
        "G": 406.18,
        "E": 8576.92,
        "D": 3616.8
      },
      "por_status": {
        "B": 20134.36,
        "P": 10593.77,
        "C": 24771.98,
        "D": 34005.53,
        "A": 22116.02
      },
      "por_placa": {
        "AXB855": 1721.41,
        "APC840": 2023.22,
        "AWC785": 3080.79,
        "ATP870": 2455.99,
        "C8F736": 1292.92,
        "ASM907": 1959.01,
        "F3M892": 2186.29,
        "ATB831": 3401.04,
        "P4A742": 3766.37,
        "C5R934": 1629.93,
        "APU790": 1588.48,
        "AMQ791": 2021.91,
        "D0I718": 1131.74,
        "BKV855": 1542.29,
        "D2H719": 2663.21,
        "F7X829": 1216.55,
        "A5K897": 2189.88,
        "ASM812": 1616.83,
        "F9W785": 1845.97,
        "ASA790": 2121.74,
        "D9G880": 1478.36,
        "D7L941": 3656.37,
        "F7B746": 2313.39,
        "A6P899": 1842.89,
        "AMF737": 1864.73,
        "C1J747": 2242.65,
        "F3V817": 1568.14,
        "APB825": 2592.02,
        "AWH909": 1614.98,
        "D3L703": 3648.97,
        "A1Q874": 2857.35,
        "CKI862": 1707.6,
        "C3Q769": 2162.08,
        "ACX716": 1860.57,
        "ARZ862": 2490.2,
        "V2F841": 2404.15,
        "D1V932": 2579.85,
        "B0V924": 1321.59,
        "AUP711": 3826.24,
        "ARD784": 2396.26,
        "A7Y808": 1402.78,
        "F1E927": 3376.31,
        "A4G840": 1259.51,
        "AVA931": 1915.39,
        "T6F869": 1561.7,
        "A5Y854": 2761.38,
        "AXH708": 3576.59,
        "C5G823": 3386.62,
        "D4R705": 1344.5,
        "BBI909": 1929.33,
        "C2B801": 1223.57
      },
      "por_almacen": {
        "ABARROTES": 96351.32,
        "REFRIGERADOS": 15270.33
      },
      "por_estado": {
        "Picking_Regular": 75823.49,
        "Picking Directo": 35798.16
      },
      "total_kg": 111621.65,
      "total_registros": 5094
    },
    "2026-07-07": {
      "por_familia": {
        "A": 32264.82,
        "C": 27161.21,
        "B": 32284.29,
        "F": 7943.43,
        "G": 552.12,
        "E": 13113.01,
        "D": 4458.35
      },
      "por_status": {
        "P": 14668.23,
        "D": 39999.99,
        "C": 22762.66,
        "A": 22090.44,
        "B": 18255.92
      },
      "por_placa": {
        "AHX902": 2597.91,
        "APB825": 2496.68,
        "ATB831": 1697.31,
        "C1J747": 2079.85,
        "F7X829": 1693.6,
        "AMQ791": 1537.42,
        "D7L941": 1733.96,
        "C5G823": 1046.47,
        "P4A742": 1971.27,
        "B0V924": 1392.04,
        "T6F869": 2288.82,
        "A6R946": 2105.4,
        "AWH909": 1933.25,
        "D2H719": 1348.2,
        "D0I718": 2784.56,
        "ARZ862": 1760.4,
        "C5R934": 1799.55,
        "D1V932": 3189.53,
        "AWC785": 1189.39,
        "ATP870": 1824.81,
        "F9W785": 1439.44,
        "AXH708": 3484.03,
        "A7Y808": 2505.42,
        "C3Q769": 2274.53,
        "D9G880": 2022.09,
        "A5K897": 2405.18,
        "F3V817": 1999.11,
        "C8F736": 2183.87,
        "A4G840": 3042.87,
        "F3M892": 1740.71,
        "AXB855": 1919.06,
        "BKV855": 1709.88,
        "ASM907": 2656.62,
        "F1E927": 1924.61,
        "APC840": 2906.42,
        "ASA790": 2803.18,
        "V2F841": 3288.54,
        "APU790": 3292.79,
        "AUP711": 1192.1,
        "ASM812": 2149.62,
        "C2B801": 2904.04,
        "D3L703": 2301.17,
        "AMF737": 2358.78,
        "AVA931": 2119.37,
        "D4R705": 2001.27,
        "F7B746": 1260.11,
        "ACX716": 2742.34,
        "A1Q874": 2077.19,
        "BBI909": 3495.08,
        "A5Y854": 3474.09,
        "A6P899": 1904.22,
        "ARD784": 2744.17,
        "CKI862": 2984.9
      },
      "por_almacen": {
        "ABARROTES": 96720.79,
        "REFRIGERADOS": 21056.44
      },
      "por_estado": {
        "Picking_Regular": 74069.59,
        "Picking Directo": 43707.64
      },
      "total_kg": 117777.23,
      "total_registros": 5592
    },
    "2026-06-08": {
      "por_familia": {
        "B": 20355.45,
        "A": 55904.16,
        "C": 22713.59,
        "F": 6806.85,
        "G": 273.98,
        "E": 8757.94,
        "D": 3431.41
      },
      "por_status": {
        "A": 43292.99,
        "B": 33295.25,
        "C": 32211.28,
        "PEN": 9443.87
      },
      "por_placa": {
        "ANI940": 1706.44,
        "D7L941": 2939.52,
        "F7X829": 2640.93,
        "T6F869": 1741.3,
        "A6R946": 2362.59,
        "C5R934": 2529.68,
        "C1J747": 2756.6,
        "A5Y854": 3065.9,
        "D4R705": 2796.68,
        "V2F841": 3496.96,
        "A1Q874": 2933.08,
        "C3Q769": 3181.29,
        "P4A742": 3156.18,
        "ACX716": 1292.66,
        "AUP711": 2799.35,
        "F1E927": 2320.07,
        "BBI909": 3795.31,
        "ASA790": 1979.45,
        "ARD784": 2288.11,
        "ASM907": 1778.96,
        "AXH708": 3187.61,
        "C5G823": 3375.89,
        "APC840": 2178.41,
        "B0V924": 2579.25,
        "ATP870": 1332.85,
        "AWC785": 1680.28,
        "D3L703": 2878.22,
        "C8F736": 3338.14,
        "F7B746": 1932.19,
        "F9W785": 1891.88,
        "A7Y808": 1215.29,
        "A4G840": 2065.66,
        "ARZ862": 1700.19,
        "APU790": 3368.59,
        "D0I718": 1603.41,
        "A6P899": 1472.6,
        "D9G880": 1643.55,
        "BKV855": 1936.14,
        "C2B801": 1728.55,
        "F3M892": 1501.32,
        "A5K897": 1880.38,
        "AXB855": 1813.41,
        "AMF737": 1873.65,
        "D1V932": 2977.83,
        "AMQ791": 2527.38,
        "W6L701": 2376.16,
        "CKI862": 2712.56,
        "AWH909": 2402.04,
        "AHX902": 2196.3,
        "APB825": 1384.39,
        "ATB831": 1928.22
      },
      "por_almacen": {
        "ABARROTES": 102704.29,
        "REFRIGERADOS": 15539.09
      },
      "por_estado": {
        "Picking_Regular": 72258.53,
        "Picking Directo": 45984.85
      },
      "total_kg": 118243.38,
      "total_registros": 4913
    },
    "2026-07-08": {
      "por_familia": {
        "B": 39856.55,
        "A": 38252.58,
        "C": 24919.65,
        "F": 8541.01,
        "E": 18052.01,
        "D": 3682.26,
        "G": 457.07
      },
      "por_status": {
        "A": 23514.36,
        "C": 27095.4,
        "D": 45047.35,
        "B": 24834.98,
        "P": 13269.06
      },
      "por_placa": {
        "A7Y808": 3079.41,
        "ATP870": 3267.11,
        "BBI909": 2234.32,
        "D0I718": 2617.44,
        "C5G823": 2548.49,
        "ACX716": 1885.63,
        "BKV855": 2135.29,
        "D4R705": 3382.05,
        "F3V817": 1891.07,
        "A4G840": 3536.68,
        "F3M892": 2072.89,
        "D9G880": 2302.67,
        "ARD784": 3410.2,
        "ASM907": 2859.8,
        "A1Q874": 2545.81,
        "APU790": 3567.52,
        "AMQ791": 2285.37,
        "C1J747": 1698.91,
        "AUP711": 2959.93,
        "T6F869": 2310.99,
        "D1V932": 2365.65,
        "F9W785": 2565.98,
        "A6P899": 2813.63,
        "CKI862": 2602.6,
        "APB825": 3454.83,
        "D7L941": 3070.96,
        "F7B746": 1437.43,
        "AXB855": 1315.44,
        "AHX902": 3042.58,
        "ASA790": 2092.39,
        "A5Y854": 2043.03,
        "F7X829": 2658.19,
        "ATB831": 3202.98,
        "AMF737": 3385.56,
        "A5K897": 2209.69,
        "AXH708": 1739.15,
        "P4A742": 3664.58,
        "B0V924": 1941.65,
        "A6R946": 2507.74,
        "F1E927": 1399.57,
        "APC840": 2642.35,
        "D3L703": 3337.51,
        "ARZ862": 1998.48,
        "C5R934": 3624.83,
        "C2B801": 1247.79,
        "D2H719": 1586.91,
        "C3Q769": 2497.15,
        "C8F736": 2390.74,
        "ASM812": 2078.72,
        "AWC785": 1023.7,
        "AWH909": 3372.02,
        "V2F841": 2767.29,
        "AVA931": 3088.47
      },
      "por_almacen": {
        "ABARROTES": 107168.11,
        "REFRIGERADOS": 26593.03
      },
      "por_estado": {
        "Picking_Regular": 83075.29,
        "Picking Directo": 50685.85
      },
      "total_kg": 133761.14,
      "total_registros": 5516
    },
    "2026-06-09": {
      "por_familia": {
        "B": 26827.01,
        "A": 34892.46,
        "C": 30797.21,
        "F": 6462.53,
        "G": 580.81,
        "D": 4093.44,
        "E": 15926.66
      },
      "por_status": {
        "A": 41288.72,
        "B": 27233.2,
        "C": 35068.13,
        "PEN": 15990.07
      },
      "por_placa": {
        "AXB855": 2426.53,
        "ATP870": 1925.58,
        "D7L941": 2305.55,
        "D9G880": 2435.52,
        "A6R946": 1762.97,
        "ASM907": 1651.82,
        "AXH708": 2658.53,
        "A4G840": 2444.28,
        "F1E927": 2366.3,
        "AMQ791": 2354.14,
        "W6L701": 3080.09,
        "C2B801": 3539.37,
        "ANI940": 1788.51,
        "APC840": 1730.7,
        "T6F869": 1729.55,
        "ASM812": 1691.94,
        "P4A742": 3125.96,
        "BKV855": 3226.08,
        "A6P899": 1636.01,
        "D2H719": 4233.19,
        "F7B746": 2184.97,
        "APU790": 2821.11,
        "ATB831": 2655.25,
        "ASA790": 2543.42,
        "C3Q769": 1543.83,
        "ACX716": 3124.1,
        "A7Y808": 2036.16,
        "ARZ862": 3734.42,
        "D0I718": 1645.66,
        "C1J747": 1400.0,
        "D4R705": 2358.18,
        "APB825": 3169.44,
        "A5Y854": 2133.53,
        "B0V924": 1629.79,
        "AWC785": 1729.82,
        "D3L703": 1648.26,
        "C5G823": 2976.4,
        "C5R934": 1869.52,
        "D1V932": 3195.65,
        "C8F736": 2397.38,
        "V2F841": 3752.14,
        "A5K897": 1621.41,
        "AWH909": 2101.22,
        "F3M892": 1574.51,
        "CKI862": 1483.67,
        "ARD784": 1924.79,
        "F9W785": 1616.44,
        "F7X829": 1621.16,
        "A1Q874": 1398.98,
        "AUP711": 2143.65,
        "BBI909": 3166.33,
        "AHX902": 2266.32
      },
      "por_almacen": {
        "ABARROTES": 97238.07,
        "REFRIGERADOS": 22342.06
      },
      "por_estado": {
        "Picking_Regular": 75004.94,
        "Picking Directo": 44575.18
      },
      "total_kg": 119580.12,
      "total_registros": 5384
    },
    "2026-07-09": {
      "por_familia": {
        "B": 36852.03,
        "A": 32384.74,
        "C": 23784.54,
        "F": 8784.2,
        "G": 445.31,
        "D": 5292.91,
        "E": 16972.75
      },
      "por_status": {
        "D": 39694.17,
        "C": 27380.55,
        "A": 21792.78,
        "B": 23974.99,
        "P": 11673.99
      },
      "por_placa": {
        "ASA790": 1852.33,
        "D2H719": 2317.63,
        "ASM907": 1927.45,
        "D0I718": 3095.49,
        "A5K897": 2085.62,
        "CKI862": 2706.98,
        "APC840": 2055.65,
        "APB825": 2753.21,
        "F7X829": 2852.99,
        "D7L941": 1997.34,
        "AHX902": 2442.16,
        "AMF737": 3205.74,
        "A4G840": 1829.47,
        "BBI909": 2364.56,
        "C8F736": 1980.52,
        "A1Q874": 1455.05,
        "APU790": 1962.48,
        "D3L703": 2573.89,
        "C5R934": 1517.15,
        "F3V817": 1600.55,
        "AUP711": 2239.19,
        "BKV855": 2351.11,
        "D9G880": 3002.04,
        "ARZ862": 1533.48,
        "C5G823": 3553.01,
        "C3Q769": 2336.54,
        "ATB831": 2376.85,
        "AWH909": 4040.85,
        "AXH708": 3399.55,
        "F3M892": 1762.07,
        "B0V924": 2317.64,
        "F9W785": 2625.36,
        "P4A742": 3072.75,
        "A6P899": 3119.41,
        "ATP870": 2918.1,
        "F7B746": 2781.04,
        "T6F869": 2139.4,
        "A5Y854": 2463.2,
        "AXB855": 1475.66,
        "AVA931": 1962.56,
        "A6R946": 2404.43,
        "A7Y808": 2233.48,
        "D4R705": 1870.59,
        "ACX716": 1731.22,
        "AWC785": 1176.67,
        "F1E927": 2163.25,
        "ASM812": 1311.04,
        "V2F841": 3387.8,
        "D1V932": 2241.31,
        "C1J747": 2296.42,
        "AMQ791": 3084.2,
        "ARD784": 2484.92,
        "C2B801": 2085.05
      },
      "por_almacen": {
        "ABARROTES": 98759.52,
        "REFRIGERADOS": 25756.95
      },
      "por_estado": {
        "Picking_Regular": 80509.02,
        "Picking Directo": 44007.45
      },
      "total_kg": 124516.48,
      "total_registros": 5703
    },
    "2026-06-10": {
      "por_familia": {
        "B": 29872.56,
        "A": 39363.11,
        "C": 28542.48,
        "F": 7191.11,
        "G": 561.89,
        "E": 21802.3,
        "D": 4278.33
      },
      "por_status": {
        "C": 37029.28,
        "PEN": 24359.09,
        "A": 37131.56,
        "B": 33091.85
      },
      "por_placa": {
        "A1Q874": 1646.22,
        "AMF737": 2861.61,
        "BBI909": 2041.63,
        "F7X829": 2065.09,
        "D7L941": 2798.55,
        "AXH708": 1768.67,
        "ASM907": 1981.52,
        "ANI940": 1613.74,
        "D0I718": 2566.51,
        "D1V932": 2185.88,
        "F7B746": 1976.48,
        "C5G823": 2552.69,
        "T6F869": 2150.39,
        "AMQ791": 1658.93,
        "C2B801": 3920.15,
        "CKI862": 2620.78,
        "AWC785": 2097.06,
        "ARZ862": 2064.99,
        "D3L703": 2829.89,
        "W6L701": 1744.01,
        "A7Y808": 1981.65,
        "F9W785": 1734.26,
        "APU790": 3355.47,
        "C5R934": 2598.33,
        "W2B907": 2988.61,
        "AVA931": 5096.79,
        "A5Y854": 2265.55,
        "D2H719": 1679.1,
        "ACX716": 2053.74,
        "C3Q769": 1739.04,
        "A5K897": 1821.58,
        "C8F736": 2884.81,
        "D4R705": 3261.95,
        "B0V924": 1485.49,
        "BKV855": 2066.63,
        "F1E927": 1459.91,
        "ATP870": 2783.98,
        "ASM812": 1799.44,
        "AXB855": 1629.44,
        "A6P899": 2501.77,
        "V2F841": 1998.02,
        "A6R946": 3026.95,
        "C1J747": 3291.69,
        "APC840": 2268.53,
        "APB825": 2590.43,
        "F3M892": 1344.38,
        "P4A742": 2442.3,
        "A4G840": 2343.22,
        "D9G880": 1870.74,
        "AWH909": 3382.4,
        "ATB831": 2805.18,
        "ASA790": 2273.55,
        "ARD784": 2819.08,
        "AHX902": 3406.25,
        "AUP711": 3416.73
      },
      "por_almacen": {
        "ABARROTES": 102664.65,
        "REFRIGERADOS": 28947.14
      },
      "por_estado": {
        "Picking_Regular": 79294.21,
        "Picking Directo": 52317.57
      },
      "total_kg": 131611.79,
      "total_registros": 5571
    },
    "2026-07-10": {
      "por_familia": {
        "B": 23921.34,
        "A": 27200.48,
        "C": 20265.23,
        "F": 6805.0,
        "G": 452.09,
        "E": 10629.23,
        "D": 3555.64
      },
      "por_status": {
        "P": 4907.32,
        "D": 33983.72,
        "A": 16424.21,
        "C": 16768.94,
        "B": 20744.83
      },
      "por_placa": {
        "D9G880": 1111.81,
        "AXB855": 2061.4,
        "ARZ862": 1819.58,
        "A5K897": 2679.52,
        "ACX716": 2110.38,
        "A7Y808": 1978.08,
        "A1Q874": 1858.12,
        "D2H719": 1214.71,
        "D3L703": 1602.58,
        "CKI862": 1714.22,
        "F7X829": 2546.92,
        "ASA790": 2541.65,
        "AHX902": 1871.28,
        "A4G840": 2135.99,
        "D7L941": 2009.34,
        "F7B746": 1476.42,
        "F9W785": 2233.94,
        "C8F736": 2107.31,
        "ATB831": 2058.16,
        "ARD784": 1627.62,
        "D0I718": 1654.03,
        "C5G823": 1596.0,
        "ASM812": 1700.9,
        "V2F841": 3089.37,
        "AMF737": 1645.49,
        "AUP711": 2638.63,
        "AXH708": 1674.91,
        "F3V817": 2615.35,
        "A6R946": 1845.43,
        "A5Y854": 1884.23,
        "T6F869": 1318.14,
        "ASM907": 1951.14,
        "B0V924": 1454.31,
        "A6P899": 1474.6,
        "C2B801": 3434.94,
        "APU790": 1328.85,
        "AWC785": 1658.23,
        "C5R934": 1045.81,
        "BBI909": 2388.5,
        "ATP870": 1529.94,
        "C1J747": 1569.41,
        "P4A742": 1753.73,
        "AMQ791": 1426.29,
        "C3Q769": 1407.0,
        "APB825": 1250.46,
        "F1E927": 1343.51,
        "D4R705": 1314.96,
        "BKV855": 1548.57,
        "APC840": 1498.11,
        "D1V932": 1236.28,
        "AWH909": 1792.85
      },
      "por_almacen": {
        "ABARROTES": 75394.79,
        "REFRIGERADOS": 17434.23
      },
      "por_estado": {
        "Picking_Regular": 65840.1,
        "Picking Directo": 26988.92
      },
      "total_kg": 92829.02,
      "total_registros": 5331
    },
    "2026-06-11": {
      "por_familia": {
        "B": 30605.58,
        "A": 30228.72,
        "C": 31185.78,
        "F": 7652.95,
        "G": 422.7,
        "E": 19009.7,
        "D": 4339.43
      },
      "por_status": {
        "A": 48955.78,
        "B": 35780.69,
        "P": 7352.46,
        "C": 31355.95
      },
      "por_placa": {
        "ASM907": 3122.9,
        "ANI940": 2541.34,
        "ATP870": 1932.07,
        "AMQ791": 2035.48,
        "ARZ862": 1596.67,
        "A6P899": 1552.81,
        "AXH708": 3141.34,
        "F7X829": 2500.15,
        "W6L701": 2202.52,
        "C5G823": 3105.96,
        "D0I718": 2610.17,
        "C2B801": 3559.22,
        "C3Q769": 1443.44,
        "A4G840": 2813.09,
        "F9W785": 3157.66,
        "BBI909": 2124.83,
        "C8F736": 2490.68,
        "F7B746": 1927.23,
        "C5R934": 1819.7,
        "A5K897": 2594.32,
        "T6F869": 2285.97,
        "AHX902": 2293.44,
        "AMF737": 2292.62,
        "BKV855": 2051.5,
        "AWC785": 1394.66,
        "AVA931": 2293.76,
        "A6R946": 1638.36,
        "D2H719": 1953.83,
        "A1Q874": 2953.59,
        "D4R705": 1898.13,
        "APU790": 1499.47,
        "A5Y854": 2852.05,
        "ACX716": 1590.11,
        "D9G880": 2740.22,
        "C1J747": 1985.69,
        "D1V932": 2141.37,
        "B0V924": 1699.38,
        "V2F841": 2242.34,
        "F3M892": 1757.02,
        "ASM812": 1208.97,
        "D3L703": 2992.21,
        "F1E927": 1733.47,
        "CKI862": 2815.7,
        "APC840": 2285.02,
        "A7Y808": 3217.68,
        "D7L941": 3247.9,
        "AUP711": 2870.33,
        "AXB855": 1822.34,
        "ARD784": 2918.76,
        "APB825": 2655.68,
        "P4A742": 2086.05,
        "AWH909": 2089.28,
        "ASA790": 1457.98,
        "ATB831": 2208.35
      },
      "por_almacen": {
        "ABARROTES": 96831.08,
        "REFRIGERADOS": 26613.8
      },
      "por_estado": {
        "Picking_Regular": 81693.77,
        "Picking Directo": 41751.1
      },
      "total_kg": 123444.87,
      "total_registros": 5662
    },
    "2026-07-11": {
      "por_familia": {
        "B": 25471.71,
        "A": 29007.3,
        "C": 20938.85,
        "F": 7150.15,
        "G": 433.49,
        "E": 11253.61,
        "D": 3638.83
      },
      "por_status": {
        "B": 18652.72,
        "D": 28963.8,
        "P": 9679.22,
        "A": 17364.91,
        "C": 23233.28
      },
      "por_placa": {
        "D4R705": 2012.7,
        "APC840": 2826.09,
        "A5K897": 1810.07,
        "F7X829": 2001.92,
        "A6R946": 2125.57,
        "CKI862": 1756.54,
        "P4A742": 2182.89,
        "T6F869": 1401.15,
        "AXB855": 2385.97,
        "BBI909": 2001.99,
        "D9G880": 2641.58,
        "BKV855": 1678.5,
        "F9W785": 1604.76,
        "D1V932": 2156.99,
        "B0V924": 1344.78,
        "APB825": 2037.79,
        "ASA790": 2685.05,
        "AUP711": 2649.27,
        "D3L703": 2457.39,
        "ASM907": 1636.46,
        "A7Y808": 1439.1,
        "ATB831": 2433.3,
        "AHX902": 2255.53,
        "AXH708": 1959.75,
        "C8F736": 1315.46,
        "ARD784": 2565.76,
        "ARZ862": 1610.88,
        "AMF737": 1922.25,
        "A6P899": 1305.97,
        "C1J747": 2372.26,
        "D0I718": 1857.69,
        "APU790": 1952.93,
        "C3Q769": 2470.14,
        "C2B801": 2235.35,
        "D2H719": 2228.99,
        "F3V817": 1709.89,
        "F7B746": 1237.18,
        "A1Q874": 1459.39,
        "AWC785": 1897.96,
        "ATP870": 1217.17,
        "A4G840": 2247.71,
        "A5Y854": 1655.08,
        "D7L941": 1936.39,
        "F1E927": 2626.53,
        "C5R934": 3668.28,
        "ACX716": 1814.15,
        "V2F841": 1544.35,
        "AWH909": 3557.01
      },
      "por_almacen": {
        "ABARROTES": 79490.16,
        "REFRIGERADOS": 18403.76
      },
      "por_estado": {
        "Picking_Regular": 67372.0,
        "Picking Directo": 30521.92
      },
      "total_kg": 97893.92,
      "total_registros": 4979
    },
    "2026-06-12": {
      "por_familia": {
        "B": 21667.08,
        "C": 31275.27,
        "A": 31561.31,
        "F": 7216.73,
        "G": 471.3,
        "D": 3967.86,
        "E": 15249.16
      },
      "por_status": {
        "A": 40144.86,
        "B": 32586.58,
        "C": 29324.11,
        "P": 9353.16
      },
      "por_placa": {
        "AXB855": 2181.1,
        "A1Q874": 1161.62,
        "AMQ791": 1803.08,
        "A7Y808": 2907.17,
        "A6R946": 3396.05,
        "F3M892": 1292.65,
        "ATP870": 1760.8,
        "ASM907": 2005.51,
        "B0V924": 1406.79,
        "CKI862": 1062.4,
        "AXH708": 1878.95,
        "ANI940": 2310.06,
        "D2H719": 3864.12,
        "C8F736": 2469.87,
        "P4A742": 1388.59,
        "C2B801": 2532.85,
        "F9W785": 1643.85,
        "D7L941": 2687.89,
        "AHX902": 1812.08,
        "C3Q769": 1791.96,
        "F7B746": 2232.2,
        "ARZ862": 1587.39,
        "A4G840": 2215.16,
        "F1E927": 1755.25,
        "APC840": 1802.45,
        "W6L701": 1749.98,
        "BKV855": 2648.21,
        "ARD784": 1805.62,
        "D0I718": 2132.48,
        "T6F869": 1995.16,
        "APU790": 2023.39,
        "D4R705": 1939.73,
        "ATB831": 2337.63,
        "C1J747": 1418.16,
        "A5Y854": 1886.83,
        "ASM812": 1451.19,
        "APB825": 3142.83,
        "C5G823": 3872.39,
        "AWC785": 1324.24,
        "V2F841": 3019.78,
        "C5R934": 2095.79,
        "D1V932": 1883.56,
        "AMF737": 1552.7,
        "D9G880": 1798.11,
        "A6P899": 1580.75,
        "A5K897": 2711.53,
        "D3L703": 1618.9,
        "ASA790": 1695.51,
        "F7X829": 2036.45,
        "AUP711": 2972.95,
        "AWH909": 2318.8,
        "ACX716": 2557.92,
        "BBI909": 2888.27
      },
      "por_almacen": {
        "ABARROTES": 88974.54,
        "REFRIGERADOS": 22434.18
      },
      "por_estado": {
        "Picking_Regular": 78436.57,
        "Picking Directo": 32972.14
      },
      "total_kg": 111408.72,
      "total_registros": 5482
    },
    "2026-06-13": {
      "por_familia": {
        "B": 21394.01,
        "A": 31945.41,
        "C": 30087.76,
        "F": 8989.29,
        "G": 529.59,
        "E": 15759.49,
        "D": 3561.69
      },
      "por_status": {
        "B": 36992.81,
        "PE": 8809.21,
        "C": 24629.86,
        "A": 41835.35
      },
      "por_placa": {
        "F1E927": 2782.11,
        "ANI940": 1986.58,
        "APU790": 2411.3,
        "D0I718": 2678.38,
        "ASM907": 1586.36,
        "D7L941": 2908.25,
        "AXH708": 2298.97,
        "A1Q874": 3278.87,
        "F9W785": 3271.32,
        "A5K897": 1203.71,
        "P4A742": 2124.45,
        "CKI862": 1698.42,
        "F7B746": 1325.16,
        "AHX902": 1504.16,
        "D9G880": 2627.73,
        "T6F869": 1871.13,
        "AMF737": 2565.16,
        "A7Y808": 1884.43,
        "A6P899": 2297.85,
        "C1J747": 1687.51,
        "AXB855": 2724.54,
        "C8F736": 1748.22,
        "ACX716": 1645.55,
        "C2B801": 2686.62,
        "B0V924": 1310.78,
        "D4R705": 2634.01,
        "W6L701": 1622.17,
        "BKV855": 2502.78,
        "A6R946": 1510.23,
        "APC840": 2564.85,
        "A5Y854": 2541.27,
        "D1V932": 2495.95,
        "ARZ862": 2077.17,
        "D3L703": 2256.0,
        "AWC785": 1882.57,
        "ASM812": 2097.11,
        "V2F841": 1690.84,
        "ATP870": 1779.54,
        "ASA790": 2329.41,
        "F3M892": 1577.19,
        "D2H719": 2514.83,
        "APB825": 1405.72,
        "A4G840": 2666.55,
        "ATB831": 2335.08,
        "AMQ791": 2488.09,
        "C3Q769": 1536.48,
        "AWH909": 3932.46,
        "BBI909": 3196.83,
        "ARD784": 2876.07,
        "AUP711": 3646.48
      },
      "por_almacen": {
        "ABARROTES": 87527.02,
        "REFRIGERADOS": 24740.21
      },
      "por_estado": {
        "Picking_Regular": 77609.05,
        "Picking Directo": 34658.19
      },
      "total_kg": 112267.23,
      "total_registros": 5118
    },
    "2026-07-13": {
      "por_familia": {
        "B": 34283.32,
        "A": 27166.6,
        "C": 22145.99,
        "F": 6891.68,
        "E": 11044.56,
        "G": 331.7,
        "D": 3062.97
      },
      "por_status": {
        "B": 23628.31,
        "D": 27404.39,
        "P": 15053.87,
        "A": 16582.42,
        "C": 22257.84
      },
      "por_placa": {
        "APC840": 1730.13,
        "C8F736": 1700.23,
        "D7L941": 1907.87,
        "ASM907": 1856.0,
        "AHX902": 1800.88,
        "ATB831": 1944.28,
        "C5G823": 3236.96,
        "A4G840": 1526.86,
        "V2F841": 2303.83,
        "C5R934": 3033.36,
        "APU790": 4053.58,
        "AMQ791": 2117.2,
        "D0I718": 1370.52,
        "P4A742": 4142.13,
        "D2H719": 2320.93,
        "F7B746": 1968.88,
        "ASM812": 1280.03,
        "AWC785": 1697.77,
        "AMF737": 1563.26,
        "F9W785": 1739.31,
        "ASA790": 2209.05,
        "D9G880": 1601.92,
        "D4R705": 1388.81,
        "T6F869": 2381.48,
        "APB825": 2623.17,
        "F7X829": 1651.69,
        "A6P899": 1616.07,
        "AXB855": 1559.4,
        "C1J747": 2964.54,
        "F3V817": 1822.54,
        "AWH909": 2752.07,
        "A1Q874": 2376.88,
        "C3Q769": 2301.65,
        "AUP711": 2783.76,
        "CKI862": 1428.35,
        "A5K897": 1637.16,
        "ACX716": 1032.71,
        "BKV855": 1041.05,
        "AVA931": 1656.47,
        "ARZ862": 1292.54,
        "D1V932": 1994.52,
        "A5Y854": 1868.67,
        "B0V924": 1048.27,
        "A7Y808": 1391.38,
        "W6L701": 3167.86,
        "D3L703": 3733.22,
        "BBI909": 2024.03,
        "AXH708": 3007.3,
        "ATP870": 1458.5,
        "A6R946": 1571.45,
        "ARD784": 2246.28
      },
      "por_almacen": {
        "ABARROTES": 86990.59,
        "REFRIGERADOS": 17936.24
      },
      "por_estado": {
        "Picking_Regular": 65139.15,
        "Picking Directo": 39787.68
      },
      "total_kg": 104926.83,
      "total_registros": 5013
    },
    "2026-07-14": {
      "por_familia": {
        "B": 32986.37,
        "A": 23581.31,
        "C": 27226.14,
        "F": 6580.24,
        "G": 490.8,
        "E": 9970.33,
        "D": 4743.95
      },
      "por_status": {
        "D": 28518.56,
        "B": 22567.15,
        "C": 22746.69,
        "A": 20805.86,
        "P": 10940.89
      },
      "por_placa": {
        "A5K897": 2660.68,
        "W6L701": 3021.03,
        "ATP870": 1644.8,
        "AXB855": 1312.63,
        "APC840": 2596.42,
        "T6F869": 2333.66,
        "ASA790": 2286.43,
        "CKI862": 1424.03,
        "A4G840": 1882.35,
        "D3L703": 2897.35,
        "AMQ791": 2165.59,
        "D9G880": 2152.92,
        "D7L941": 2254.87,
        "ATB831": 1552.25,
        "P4A742": 3395.4,
        "D2H719": 1928.31,
        "D0I718": 1391.08,
        "D4R705": 1395.85,
        "C5R934": 1715.61,
        "C8F736": 2090.74,
        "A6P899": 2255.62,
        "A1Q874": 2156.95,
        "AUP711": 3078.71,
        "AWH909": 2897.25,
        "BBI909": 3435.98,
        "F3V817": 1476.96,
        "APU790": 2774.34,
        "AHX902": 2365.15,
        "V2F841": 2184.14,
        "F7X829": 2305.92,
        "ASM812": 2185.82,
        "AXH708": 1368.67,
        "F7B746": 1641.22,
        "A5Y854": 1760.68,
        "A7Y808": 2559.04,
        "APB825": 3266.58,
        "C5G823": 1867.31,
        "ASM907": 1824.55,
        "C3Q769": 1401.98,
        "ACX716": 1911.89,
        "C2B801": 3027.02,
        "AWC785": 1915.02,
        "D1V932": 1895.21,
        "F9W785": 1382.1,
        "ARZ862": 1565.26,
        "BKV855": 1495.71,
        "A6R946": 3248.81,
        "ARD784": 1605.25,
        "C1J747": 1172.0,
        "B0V924": 1452.0
      },
      "por_almacen": {
        "ABARROTES": 89028.57,
        "REFRIGERADOS": 16550.57
      },
      "por_estado": {
        "Picking_Regular": 69934.39,
        "Picking Directo": 35644.75
      },
      "total_kg": 105579.13,
      "total_registros": 5305
    },
    "2026-06-15": {
      "por_familia": {
        "B": 21260.29,
        "A": 30473.39,
        "C": 27178.47,
        "F": 7105.47,
        "G": 446.3,
        "D": 3398.58,
        "E": 16237.77
      },
      "por_status": {
        "A": 39382.5,
        "B": 32879.34,
        "C": 24571.57,
        "P": 9266.87
      },
      "por_placa": {
        "ASM812": 1950.97,
        "ASM907": 1774.99,
        "ARD784": 2131.57,
        "APC840": 2239.51,
        "F7X829": 2273.94,
        "ANI940": 1901.04,
        "C5R934": 2125.11,
        "A7Y808": 1199.15,
        "T6F869": 2426.47,
        "ACX716": 1313.76,
        "C2B801": 1434.47,
        "BKV855": 1434.35,
        "D9G880": 1994.14,
        "V2F841": 2529.74,
        "AMQ791": 2412.1,
        "A1Q874": 3203.09,
        "ATB831": 2083.55,
        "P4A742": 2432.13,
        "D2H719": 2310.44,
        "ASA790": 2214.36,
        "AHX902": 2413.13,
        "D4R705": 1656.43,
        "AXH708": 3175.31,
        "ATP870": 1562.38,
        "C5G823": 2553.4,
        "B0V924": 1476.54,
        "AWC785": 2625.05,
        "D3L703": 2810.53,
        "A6R946": 2001.12,
        "F7B746": 1881.72,
        "C8F736": 2364.93,
        "C1J747": 2999.0,
        "F9W785": 2500.9,
        "ARZ862": 2130.32,
        "A4G840": 1869.9,
        "A6P899": 1543.23,
        "APU790": 2168.46,
        "A5Y854": 2648.97,
        "D0I718": 1296.14,
        "CKI862": 1492.68,
        "A5K897": 1515.7,
        "AMF737": 1461.99,
        "AUP711": 2314.46,
        "AWH909": 1854.41,
        "AXB855": 1901.36,
        "D1V932": 3418.43,
        "C3Q769": 1670.11,
        "F1E927": 2643.61,
        "BBI909": 2115.13,
        "APB825": 2650.06
      },
      "por_almacen": {
        "ABARROTES": 82763.04,
        "REFRIGERADOS": 23337.24
      },
      "por_estado": {
        "Picking_Regular": 76539.86,
        "Picking Directo": 29560.42
      },
      "total_kg": 106100.28,
      "total_registros": 5265
    },
    "2026-07-15": {
      "por_familia": {
        "B": 29522.51,
        "C": 26236.67,
        "A": 33911.71,
        "F": 6960.31,
        "G": 520.25,
        "E": 12754.76,
        "D": 3768.09
      },
      "por_status": {
        "A": 23102.56,
        "C": 23858.05,
        "B": 23301.79,
        "D": 31577.68,
        "P": 11834.22
      },
      "por_placa": {
        "ATB831": 1997.92,
        "AUP711": 2381.81,
        "D1V932": 1930.41,
        "D3L703": 3063.75,
        "APB825": 3022.02,
        "P4A742": 2919.88,
        "A6P899": 2577.6,
        "A5Y854": 1850.39,
        "A6R946": 2278.24,
        "D0I718": 2179.03,
        "BKV855": 1954.28,
        "T6F869": 1425.11,
        "ATP870": 2664.33,
        "F7X829": 2229.27,
        "F7B746": 3114.39,
        "F9W785": 2121.08,
        "AMF737": 3139.04,
        "C2B801": 3118.54,
        "B0V924": 1785.28,
        "D4R705": 2951.78,
        "F1E927": 1682.85,
        "ASM812": 1418.19,
        "C1J747": 2345.93,
        "AHX902": 2167.61,
        "AWC785": 1279.43,
        "AMQ791": 1487.74,
        "ASA790": 2605.65,
        "C5G823": 1691.26,
        "C3Q769": 1467.4,
        "ACX716": 1488.23,
        "BBI909": 1664.52,
        "A5K897": 2008.69,
        "ARZ862": 1641.57,
        "APU790": 3492.12,
        "AXB855": 2011.43,
        "F3V817": 2020.9,
        "ASM907": 2940.42,
        "A7Y808": 2670.05,
        "D9G880": 1885.61,
        "AXH708": 1367.8,
        "C5R934": 3689.81,
        "D7L941": 3749.28,
        "A1Q874": 1891.78,
        "APC840": 2016.88,
        "AWH909": 3392.72,
        "CKI862": 2975.41,
        "ARD784": 2587.94,
        "C8F736": 1477.38,
        "V2F841": 3851.58
      },
      "por_almacen": {
        "ABARROTES": 93959.23,
        "REFRIGERADOS": 19715.08
      },
      "por_estado": {
        "Picking_Regular": 72614.61,
        "Picking Directo": 41059.7
      },
      "total_kg": 113674.31,
      "total_registros": 5136
    },
    "2026-06-16": {
      "por_familia": {
        "B": 47437.79,
        "C": 27825.58,
        "F": 9331.4,
        "G": 611.06,
        "E": 14670.54,
        "A": 26362.35,
        "D": 3531.21
      },
      "por_status": {
        "C": 31294.48,
        "P": 17109.88,
        "A": 50264.37,
        "B": 31101.19
      },
      "por_placa": {
        "A6R946": 1431.29,
        "W6L701": 2499.45,
        "AXH708": 2628.51,
        "P4A742": 3871.13,
        "A1Q874": 1665.91,
        "AWH909": 2224.37,
        "D1V932": 2205.12,
        "F1E927": 2624.77,
        "ASM907": 1266.52,
        "ARZ862": 2027.69,
        "D2H719": 3930.49,
        "A7Y808": 2265.88,
        "CKI862": 1947.68,
        "AMF737": 1919.49,
        "D7L941": 2410.57,
        "ATB831": 2444.94,
        "D0I718": 1812.04,
        "A5K897": 2738.77,
        "C1J747": 1306.07,
        "ASA790": 1953.55,
        "C2B801": 3848.4,
        "ACX716": 2574.51,
        "BBI909": 3577.46,
        "A5Y854": 2188.76,
        "A4G840": 1896.35,
        "AUP711": 4314.57,
        "B0V924": 1790.56,
        "BKV855": 1534.03,
        "ATP870": 2191.51,
        "ASM812": 1715.66,
        "C3Q769": 1555.27,
        "APB825": 3227.11,
        "V2F841": 4025.57,
        "D3L703": 2385.03,
        "APC840": 2465.56,
        "F7X829": 1936.51,
        "APU790": 2686.19,
        "ARD784": 1852.49,
        "AXB855": 1905.39,
        "F3M892": 1206.58,
        "F7B746": 1901.72,
        "D9G880": 2495.05,
        "AMQ791": 2451.3,
        "C8F736": 2961.69,
        "D4R705": 2261.04,
        "ANI940": 1369.89,
        "AHX902": 2775.05,
        "C5R934": 2126.64,
        "T6F869": 1637.21,
        "A6P899": 3141.73,
        "AWC785": 1567.58,
        "C5G823": 4226.66,
        "ANE848": 4961.28,
        "F9W785": 1841.34
      },
      "por_almacen": {
        "ABARROTES": 105799.7,
        "REFRIGERADOS": 23970.22
      },
      "por_estado": {
        "Picking_Regular": 75042.11,
        "Picking Directo": 54727.81
      },
      "total_kg": 129769.92,
      "total_registros": 5608
    },
    "2026-07-16": {
      "por_familia": {
        "B": 29674.73,
        "A": 30754.25,
        "C": 22226.88,
        "F": 6981.03,
        "G": 495.67,
        "E": 13489.11,
        "D": 4273.85
      },
      "por_status": {
        "C": 20199.12,
        "D": 30598.71,
        "B": 22789.4,
        "A": 20478.61,
        "P": 13829.68
      },
      "por_placa": {
        "AXB855": 1521.27,
        "ATB831": 1979.01,
        "ARZ862": 2067.0,
        "T6F869": 2207.37,
        "C5R934": 1814.14,
        "APB825": 1935.76,
        "APC840": 2387.14,
        "D3L703": 2550.22,
        "D7L941": 2172.17,
        "ATP870": 2353.36,
        "C1J747": 2066.08,
        "D0I718": 2776.92,
        "C5G823": 3329.87,
        "AUP711": 2231.3,
        "A5K897": 2150.05,
        "F3V817": 2342.59,
        "A4G840": 2045.62,
        "F7B746": 2290.29,
        "AWC785": 1704.59,
        "D4R705": 2009.09,
        "A1Q874": 2010.51,
        "ASM812": 1568.53,
        "ARD784": 2690.99,
        "AHX902": 2833.54,
        "ASA790": 1422.27,
        "AXH708": 3093.71,
        "ASM907": 2053.29,
        "F7X829": 2735.09,
        "ACX716": 1309.93,
        "CKI862": 2429.49,
        "BBI909": 2289.09,
        "C3Q769": 2342.46,
        "C8F736": 2056.03,
        "BKV855": 1673.01,
        "AMQ791": 2863.4,
        "D1V932": 1976.95,
        "B0V924": 2735.15,
        "D9G880": 1873.52,
        "AWH909": 2081.57,
        "P4A742": 1768.27,
        "AMF737": 2126.68,
        "F9W785": 3163.85,
        "APU790": 1688.63,
        "A5Y854": 2498.38,
        "A7Y808": 2029.1,
        "F1E927": 1811.44,
        "D2H719": 2240.78,
        "A6R946": 2684.97,
        "C2B801": 1911.03
      },
      "por_almacen": {
        "ABARROTES": 87425.39,
        "REFRIGERADOS": 20470.14
      },
      "por_estado": {
        "Picking_Regular": 72976.55,
        "Picking Directo": 34918.98
      },
      "total_kg": 107895.53,
      "total_registros": 5201
    },
    "2026-06-17": {
      "por_familia": {
        "A": 36984.83,
        "B": 47390.06,
        "C": 26395.78,
        "F": 9562.3,
        "G": 540.81,
        "E": 16147.98,
        "D": 3849.61
      },
      "por_status": {
        "B": 40148.02,
        "A": 50257.68,
        "C": 34843.4,
        "P": 15622.28
      },
      "por_placa": {
        "A1Q874": 1889.49,
        "APC840": 2980.21,
        "APB825": 3374.04,
        "C2B801": 3653.89,
        "C8F736": 3424.65,
        "D7L941": 4069.83,
        "D1V932": 2134.75,
        "F9W785": 1562.26,
        "CKI862": 1751.63,
        "F7B746": 1982.81,
        "W6L701": 3939.35,
        "C5R934": 4830.43,
        "ARZ862": 2703.07,
        "C5G823": 2200.45,
        "D2H719": 1596.19,
        "B0V924": 3442.48,
        "AXB855": 1606.65,
        "ASM812": 1629.49,
        "A4G840": 2881.81,
        "AWC785": 2723.41,
        "ATB831": 3813.03,
        "ARD784": 1981.15,
        "AUP711": 3260.56,
        "F1E927": 1412.63,
        "ASM907": 2864.08,
        "F7X829": 2291.14,
        "D4R705": 2821.63,
        "AMQ791": 1761.69,
        "C1J747": 1981.69,
        "ANI940": 2186.03,
        "AMF737": 2313.18,
        "P4A742": 3429.72,
        "D0I718": 2741.88,
        "A5Y854": 1850.38,
        "APU790": 3738.4,
        "A6R946": 3496.19,
        "ANE848": 1155.64,
        "BKV855": 2116.06,
        "AHX902": 2382.75,
        "V2F841": 3100.15,
        "ATP870": 2269.49,
        "BBI909": 2153.03,
        "T6F869": 2021.46,
        "F3M892": 3308.72,
        "D9G880": 1862.56,
        "ASA790": 1865.16,
        "A5K897": 2990.46,
        "ACX716": 1944.09,
        "AXH708": 1747.34,
        "A7Y808": 1886.49,
        "D3L703": 3614.82,
        "C3Q769": 2921.12,
        "AWH909": 3967.86,
        "AVA931": 3243.9
      },
      "por_almacen": {
        "ABARROTES": 115168.82,
        "REFRIGERADOS": 25702.57
      },
      "por_estado": {
        "Picking_Regular": 84539.69,
        "Picking Directo": 56331.69
      },
      "total_kg": 140871.39,
      "total_registros": 5546
    },
    "2026-07-17": {
      "por_familia": {
        "B": 24768.09,
        "C": 30590.52,
        "A": 30044.05,
        "F": 6347.36,
        "G": 400.5,
        "E": 11911.8,
        "D": 4400.43
      },
      "por_status": {
        "C": 23935.73,
        "D": 29083.31,
        "A": 22022.43,
        "P": 10029.81,
        "B": 23391.47
      },
      "por_placa": {
        "APB825": 1551.62,
        "ARZ862": 2373.76,
        "F9W785": 2461.73,
        "T6F869": 1455.28,
        "ATB831": 1975.42,
        "A1Q874": 3073.54,
        "A5K897": 2005.31,
        "AXH708": 1907.11,
        "A7Y808": 2485.53,
        "C5G823": 3501.69,
        "P4A742": 1968.23,
        "C2B801": 3236.37,
        "AHX902": 2470.06,
        "F3V817": 1905.12,
        "A5Y854": 1901.33,
        "D4R705": 3184.52,
        "A6P899": 3154.06,
        "AUP711": 1499.71,
        "CKI862": 1892.22,
        "B0V924": 1696.72,
        "A6R946": 2454.87,
        "D2H719": 2006.37,
        "F1E927": 2174.04,
        "AWC785": 1991.35,
        "F7B746": 2452.19,
        "V2F841": 3423.89,
        "ATP870": 2366.57,
        "C1J747": 1554.36,
        "ARD784": 2354.57,
        "D1V932": 1702.76,
        "W6L701": 1622.75,
        "ACX716": 2405.34,
        "BKV855": 1811.12,
        "F7X829": 2284.19,
        "AMF737": 2560.7,
        "D9G880": 1553.9,
        "APU790": 2186.55,
        "A4G840": 2590.03,
        "ASM907": 2077.18,
        "AMQ791": 1906.94,
        "ASA790": 1965.05,
        "C8F736": 2100.61,
        "ASM812": 1722.07,
        "AXB855": 1448.88,
        "BBI909": 3242.93,
        "C3Q769": 1973.99,
        "D3L703": 3950.34,
        "AWH909": 2879.86
      },
      "por_almacen": {
        "ABARROTES": 90203.58,
        "REFRIGERADOS": 18259.17
      },
      "por_estado": {
        "Picking_Regular": 75053.87,
        "Picking Directo": 33408.88
      },
      "total_kg": 108462.75,
      "total_registros": 5706
    },
    "2026-06-18": {
      "por_familia": {
        "B": 36895.66,
        "C": 25215.11,
        "F": 8932.63,
        "E": 15613.17,
        "A": 34079.32,
        "D": 4076.64,
        "G": 511.17
      },
      "por_status": {
        "A": 46627.52,
        "C": 31814.06,
        "B": 38406.02,
        "P": 8476.12
      },
      "por_placa": {
        "A6P899": 3505.56,
        "BBI909": 1896.75,
        "D2H719": 2282.8,
        "C1J747": 2411.01,
        "ASM812": 870.24,
        "B0V924": 1728.61,
        "F1E927": 2197.77,
        "D9G880": 2131.49,
        "AUP711": 2021.53,
        "C2B801": 3295.35,
        "ANI940": 2340.52,
        "C5G823": 3401.65,
        "F9W785": 2635.94,
        "P4A742": 3155.7,
        "APC840": 2556.47,
        "ASM907": 3344.82,
        "D0I718": 2774.09,
        "W6L701": 2102.63,
        "A5K897": 2196.17,
        "C3Q769": 1564.86,
        "A4G840": 3492.27,
        "AHX902": 3063.5,
        "A1Q874": 2383.82,
        "A6R946": 1005.62,
        "A5Y854": 2854.1,
        "D3L703": 1917.7,
        "CKI862": 1904.53,
        "D7L941": 4162.99,
        "AXB855": 1676.71,
        "AWH909": 2981.71,
        "ATB831": 1359.84,
        "C5R934": 1683.63,
        "A7Y808": 3455.38,
        "T6F869": 2353.5,
        "AMQ791": 2913.46,
        "F7B746": 1836.17,
        "APB825": 2600.68,
        "APU790": 1471.06,
        "F7X829": 2189.06,
        "D1V932": 1375.36,
        "ASA790": 1589.59,
        "BKV855": 1947.28,
        "V2F841": 2345.87,
        "AMF737": 2011.44,
        "ATP870": 3194.81,
        "ARZ862": 3157.4,
        "AXH708": 3402.25,
        "C8F736": 3056.57,
        "D4R705": 2509.44,
        "AWC785": 2065.48,
        "ACX716": 1308.59,
        "F3M892": 1210.74,
        "ARD784": 2429.2
      },
      "por_almacen": {
        "ABARROTES": 100802.76,
        "REFRIGERADOS": 24520.95
      },
      "por_estado": {
        "Picking_Regular": 75818.05,
        "Picking Directo": 49505.65
      },
      "total_kg": 125323.71,
      "total_registros": 5525
    },
    "2026-06-19": {
      "por_familia": {
        "A": 28111.67,
        "C": 24939.38,
        "F": 7064.55,
        "G": 483.73,
        "B": 27426.68,
        "E": 7872.22,
        "D": 4183.25
      },
      "por_status": {
        "A": 36819.69,
        "C": 25034.68,
        "B": 29721.56,
        "P": 8505.54
      },
      "por_placa": {
        "C3Q769": 1658.09,
        "A6R946": 1997.39,
        "ARZ862": 2852.63,
        "C1J747": 1516.44,
        "AXH708": 1900.33,
        "ACX716": 2578.19,
        "CKI862": 1319.98,
        "F3M892": 1800.59,
        "ASA790": 1229.33,
        "A5K897": 2616.24,
        "AUP711": 1729.02,
        "A6P899": 1858.09,
        "ATP870": 1892.29,
        "A4G840": 2196.31,
        "APU790": 2365.28,
        "D9G880": 2928.18,
        "T6F869": 1936.84,
        "C5R934": 1914.64,
        "B0V924": 1871.33,
        "A7Y808": 1896.04,
        "A5Y854": 1495.19,
        "P4A742": 1258.52,
        "F1E927": 1605.32,
        "D1V932": 1529.47,
        "ATB831": 2447.76,
        "F9W785": 1704.58,
        "APC840": 2070.62,
        "D7L941": 2525.96,
        "D4R705": 1561.45,
        "F7X829": 2522.36,
        "V2F841": 1783.92,
        "C8F736": 2410.26,
        "BKV855": 1601.5,
        "C5G823": 4305.82,
        "D3L703": 2494.29,
        "W6L701": 1210.19,
        "AMF737": 1351.37,
        "D0I718": 1979.08,
        "APB825": 2256.37,
        "AWC785": 1051.13,
        "ASM907": 2004.78,
        "F7B746": 2077.3,
        "AMQ791": 1432.25,
        "BBI909": 3278.89,
        "ARD784": 1615.24,
        "AWH909": 928.25,
        "C2B801": 1937.17,
        "AHX902": 2096.12,
        "ANI940": 1814.2,
        "AXB855": 1888.88,
        "A1Q874": 1785.99
      },
      "por_almacen": {
        "ABARROTES": 85176.41,
        "REFRIGERADOS": 14905.06
      },
      "por_estado": {
        "Picking_Regular": 71240.33,
        "Picking Directo": 28841.14
      },
      "total_kg": 100081.47,
      "total_registros": 5271
    },
    "2026-06-20": {
      "por_familia": {
        "A": 29366.35,
        "B": 29464.94,
        "C": 24540.42,
        "F": 7243.52,
        "E": 7378.7,
        "D": 3688.81,
        "G": 568.43
      },
      "por_status": {
        "A": 34031.15,
        "B": 30382.72,
        "C": 25925.58,
        "P": 11911.72
      },
      "por_placa": {
        "F1E927": 1645.07,
        "AXB855": 2290.2,
        "A5K897": 1590.24,
        "C1J747": 1233.45,
        "BKV855": 1634.61,
        "D7L941": 2440.42,
        "P4A742": 2996.31,
        "F9W785": 1964.17,
        "C3Q769": 3424.49,
        "ARD784": 2487.76,
        "AUP711": 2383.08,
        "A6R946": 1595.2,
        "D3L703": 2559.26,
        "A7Y808": 2148.94,
        "ARZ862": 1875.62,
        "APU790": 2291.4,
        "B0V924": 1328.18,
        "A5Y854": 1866.61,
        "A6P899": 1984.06,
        "CKI862": 1468.36,
        "AHX902": 1861.04,
        "C8F736": 1517.19,
        "ANI940": 1709.21,
        "ATP870": 1574.21,
        "ASM812": 1979.6,
        "APB825": 1113.86,
        "D2H719": 1603.33,
        "A4G840": 1887.91,
        "F7X829": 1441.48,
        "AWH909": 3535.42,
        "A1Q874": 1460.59,
        "F3M892": 1461.98,
        "AMQ791": 3373.24,
        "W6L701": 1768.26,
        "ASM907": 2021.19,
        "AWC785": 1284.5,
        "D1V932": 1379.11,
        "C5R934": 3091.51,
        "ATB831": 1905.37,
        "AXH708": 2185.68,
        "D9G880": 3643.86,
        "F7B746": 1909.64,
        "T6F869": 1404.46,
        "AMF737": 4153.4,
        "C2B801": 3445.0,
        "ACX716": 1234.82,
        "APC840": 1805.59,
        "D4R705": 1533.27,
        "ASA790": 2579.56,
        "V2F841": 1179.46
      },
      "por_almacen": {
        "ABARROTES": 87638.38,
        "REFRIGERADOS": 14612.79
      },
      "por_estado": {
        "Picking_Regular": 65644.55,
        "Picking Directo": 36606.62
      },
      "total_kg": 102251.17,
      "total_registros": 4985
    },
    "2026-06-22": {
      "por_familia": {
        "B": 26622.4,
        "A": 32181.21,
        "C": 28298.8,
        "F": 6678.85,
        "G": 226.53,
        "E": 7137.58,
        "D": 3785.94
      },
      "por_status": {
        "D": 20072.18,
        "C": 23371.43,
        "A": 19494.61,
        "B": 18593.98,
        "E": 16937.79,
        "P": 6461.32
      },
      "por_placa": {
        "ATP870": 1784.3,
        "D3L703": 1730.57,
        "C8F736": 1391.9,
        "F9W785": 1400.74,
        "A5Y854": 2057.28,
        "T6F869": 2180.92,
        "APC840": 1326.56,
        "AMF737": 3196.41,
        "D1V932": 1525.05,
        "A5K897": 1772.6,
        "F1E927": 2861.35,
        "D2H719": 2081.13,
        "ARD784": 3838.72,
        "ANI940": 2466.87,
        "ACX716": 1863.96,
        "C5R934": 2903.64,
        "F7B746": 1665.37,
        "D0I718": 1376.18,
        "A1Q874": 1221.45,
        "A7Y808": 1344.76,
        "D7L941": 1822.98,
        "D9G880": 2822.74,
        "F7X829": 1961.59,
        "ASM907": 2147.72,
        "D4R705": 2292.37,
        "BBI909": 2508.59,
        "W6L701": 1707.47,
        "AHX902": 2543.9,
        "ASA790": 2494.3,
        "A6R946": 2123.05,
        "AMQ791": 2605.16,
        "ASM812": 1244.64,
        "APU790": 1925.23,
        "P4A742": 1457.85,
        "AUP711": 1791.06,
        "B0V924": 2833.05,
        "A4G840": 1602.11,
        "AWC785": 1474.03,
        "C5G823": 1336.29,
        "A6P899": 2016.38,
        "F3M892": 1339.67,
        "ATB831": 2921.97,
        "BKV855": 1869.13,
        "C3Q769": 1793.48,
        "V2F841": 1870.31,
        "C1J747": 2127.74,
        "CKI862": 1167.81,
        "ARZ862": 1574.83,
        "AXB855": 3850.42,
        "AWH909": 2753.35,
        "AXH708": 2962.32
      },
      "por_almacen": {
        "ABARROTES": 91132.02,
        "REFRIGERADOS": 13799.28
      },
      "por_estado": {
        "Picking_Regular": 76265.0,
        "Picking Directo": 28666.31
      },
      "total_kg": 104931.31,
      "total_registros": 4980
    },
    "2026-06-23": {
      "por_familia": {
        "A": 43074.54,
        "B": 30010.25,
        "C": 28101.26,
        "F": 6187.86,
        "G": 481.94,
        "E": 10150.23,
        "D": 3407.75
      },
      "por_status": {
        "C": 25619.9,
        "A": 46174.66,
        "B": 38719.63,
        "P": 10899.65
      },
      "por_placa": {
        "A6R946": 2114.54,
        "BKV855": 2335.48,
        "W6L701": 2804.6,
        "AMF737": 1171.56,
        "P4A742": 3021.85,
        "A7Y808": 2236.19,
        "AXH708": 2060.72,
        "AWH909": 3883.75,
        "D1V932": 2519.19,
        "ASM907": 1374.6,
        "ARZ862": 2516.05,
        "ARD784": 4440.66,
        "CKI862": 1633.95,
        "ANE848": 1044.96,
        "D7L941": 1476.57,
        "A6P899": 1972.44,
        "ATB831": 2574.3,
        "A4G840": 1678.6,
        "F1E927": 2329.48,
        "C1J747": 1270.24,
        "ASA790": 1559.6,
        "C2B801": 3277.9,
        "F3M892": 2214.75,
        "ACX716": 3333.97,
        "F7B746": 2201.39,
        "BBI909": 3013.64,
        "A1Q874": 1991.55,
        "B0V924": 2927.54,
        "ATP870": 2042.98,
        "D0I718": 1569.55,
        "C3Q769": 1721.13,
        "T6F869": 1775.41,
        "D4R705": 1629.46,
        "APB825": 3235.32,
        "AWC785": 1407.34,
        "V2F841": 3809.52,
        "D3L703": 1023.5,
        "AUP711": 2885.59,
        "ASM812": 1429.3,
        "F7X829": 1587.97,
        "AHX902": 2290.09,
        "C8F736": 2003.08,
        "AMQ791": 3035.75,
        "A5K897": 2168.08,
        "ANI940": 1772.06,
        "F9W785": 1366.86,
        "D2H719": 3267.03,
        "C5R934": 1962.1,
        "D9G880": 2080.34,
        "A5Y854": 1552.96,
        "APU790": 2568.71,
        "AXB855": 1970.02,
        "APC840": 2745.45,
        "C5G823": 3534.17
      },
      "por_almacen": {
        "ABARROTES": 105089.45,
        "REFRIGERADOS": 16324.38
      },
      "por_estado": {
        "Picking_Regular": 79938.0,
        "Picking Directo": 41475.83
      },
      "total_kg": 121413.83,
      "total_registros": 5335
    },
    "2026-06-24": {
      "por_familia": {
        "B": 35273.93,
        "A": 48724.49,
        "C": 23093.67,
        "F": 6708.13,
        "G": 426.52,
        "E": 13110.6,
        "D": 3411.34
      },
      "por_status": {
        "E": 18812.04,
        "A": 17838.26,
        "C": 19846.73,
        "P": 18026.04,
        "F": 17343.45,
        "D": 20892.07,
        "B": 17990.1
      },
      "por_placa": {
        "A5Y854": 1817.34,
        "D0I718": 2162.6,
        "A5K897": 2600.81,
        "AWC785": 3126.59,
        "D7L941": 3700.44,
        "F7B746": 2153.01,
        "APU790": 2052.47,
        "V2F841": 3314.2,
        "A6R946": 2821.49,
        "AWH909": 4336.89,
        "ATB831": 3266.34,
        "B0V924": 1572.38,
        "A4G840": 2357.97,
        "F1E927": 1323.65,
        "C8F736": 2563.2,
        "ANI940": 1584.13,
        "C5G823": 1830.9,
        "ATP870": 2191.11,
        "A7Y808": 2430.42,
        "ARZ862": 3016.52,
        "ASM812": 2085.55,
        "D9G880": 2123.32,
        "C2B801": 1872.87,
        "W6L701": 1945.51,
        "APB825": 2664.51,
        "C1J747": 2700.8,
        "ASM907": 2392.91,
        "ACX716": 1904.32,
        "AHX902": 2934.4,
        "ARD784": 4776.7,
        "F7X829": 1561.09,
        "BKV855": 1955.28,
        "D1V932": 3330.73,
        "CKI862": 1544.96,
        "T6F869": 1575.7,
        "BBI909": 1785.35,
        "AMQ791": 2043.03,
        "D3L703": 3293.27,
        "A1Q874": 1322.32,
        "ASA790": 2563.1,
        "AUP711": 3752.3,
        "APC840": 1663.57,
        "AXH708": 1615.11,
        "AMF737": 2972.45,
        "C3Q769": 2381.64,
        "C5R934": 3317.25,
        "AXB855": 2057.95,
        "F9W785": 1162.37,
        "D2H719": 1345.77,
        "P4A742": 2242.55,
        "F3M892": 2542.66,
        "ANE848": 3542.41,
        "A6P899": 3072.19,
        "D4R705": 2482.3
      },
      "por_almacen": {
        "ABARROTES": 110974.52,
        "REFRIGERADOS": 19774.16
      },
      "por_estado": {
        "Picking_Regular": 84091.82,
        "Picking Directo": 46656.86
      },
      "total_kg": 130748.68,
      "total_registros": 5380
    },
    "2026-06-25": {
      "por_familia": {
        "B": 31064.43,
        "A": 40025.34,
        "C": 23937.46,
        "F": 6553.9,
        "G": 563.59,
        "E": 12265.91,
        "D": 3735.83
      },
      "por_status": {
        "C": 20269.71,
        "A": 22114.83,
        "B": 23302.64,
        "D": 25676.62,
        "P": 13136.13,
        "E": 13646.54
      },
      "por_placa": {
        "AUP711": 1225.72,
        "F7X829": 2058.61,
        "ASM907": 2647.82,
        "D0I718": 2247.66,
        "D1V932": 1534.63,
        "D2H719": 3055.24,
        "BBI909": 1540.19,
        "ASA790": 1095.0,
        "ATB831": 2602.3,
        "C5G823": 2902.14,
        "A5K897": 2750.11,
        "B0V924": 1972.67,
        "V2F841": 2316.73,
        "C5R934": 1358.56,
        "C2B801": 3178.69,
        "A6R946": 2594.84,
        "A7Y808": 2977.56,
        "C8F736": 1939.39,
        "BKV855": 1746.14,
        "D7L941": 2849.76,
        "AWH909": 2820.33,
        "F1E927": 2135.4,
        "AMF737": 1959.35,
        "AHX902": 2559.54,
        "APB825": 2716.44,
        "AWC785": 1438.37,
        "D3L703": 3346.62,
        "ASM812": 1336.99,
        "ARZ862": 2379.8,
        "APC840": 1902.93,
        "F9W785": 3057.78,
        "A4G840": 2503.95,
        "ATP870": 2766.52,
        "C3Q769": 2718.58,
        "APU790": 1818.47,
        "D9G880": 3322.19,
        "F3M892": 1282.76,
        "AXB855": 1566.77,
        "D4R705": 1452.3,
        "AXH708": 2325.84,
        "CKI862": 1804.76,
        "A1Q874": 2020.85,
        "AMQ791": 2768.1,
        "T6F869": 1967.92,
        "F7B746": 1769.84,
        "A5Y854": 2892.7,
        "ANI940": 3219.21,
        "ACX716": 1784.28,
        "C1J747": 2265.81,
        "P4A742": 2044.38,
        "ANE848": 2295.32,
        "ARD784": 3308.6
      },
      "por_almacen": {
        "ABARROTES": 99372.94,
        "REFRIGERADOS": 18773.53
      },
      "por_estado": {
        "Picking_Regular": 81632.23,
        "Picking Directo": 36514.23
      },
      "total_kg": 118146.47,
      "total_registros": 5385
    },
    "2026-06-26": {
      "por_familia": {
        "B": 23722.88,
        "C": 25681.31,
        "A": 26874.47,
        "F": 6315.51,
        "E": 10353.52,
        "G": 485.38,
        "D": 4489.15
      },
      "por_status": {
        "C": 16767.86,
        "P": 17953.31,
        "D": 26250.07,
        "B": 20695.42,
        "A": 16255.55
      },
      "por_placa": {
        "C2B801": 2965.56,
        "A5Y854": 1347.36,
        "APB825": 3419.78,
        "D1V932": 1218.06,
        "AWC785": 1574.83,
        "D3L703": 1650.59,
        "C8F736": 1912.52,
        "ATB831": 1859.08,
        "BBI909": 3382.42,
        "A6R946": 2743.42,
        "ASM812": 1361.54,
        "AMQ791": 1416.19,
        "F7X829": 2241.98,
        "ANI940": 1655.68,
        "ATP870": 1602.14,
        "AXB855": 1706.01,
        "A5K897": 2270.92,
        "C5R934": 1797.28,
        "AUP711": 2186.35,
        "B0V924": 1809.01,
        "D4R705": 1264.68,
        "ASA790": 1282.11,
        "A6P899": 2934.74,
        "A7Y808": 1408.66,
        "D7L941": 2273.29,
        "P4A742": 1810.67,
        "ACX716": 1545.83,
        "C1J747": 1453.61,
        "APU790": 2598.3,
        "ARD784": 1592.97,
        "D0I718": 1594.33,
        "AMF737": 1180.5,
        "V2F841": 1986.88,
        "AWH909": 1945.01,
        "F1E927": 1644.07,
        "ARZ862": 2161.91,
        "AXH708": 1616.42,
        "W6L701": 1092.78,
        "AHX902": 1880.64,
        "F3M892": 2560.2,
        "T6F869": 1384.06,
        "A4G840": 1764.32,
        "BKV855": 998.5,
        "CKI862": 2562.94,
        "ASM907": 1550.51,
        "D2H719": 2876.52,
        "C3Q769": 1193.6,
        "F7B746": 1693.92,
        "F9W785": 1644.85,
        "C5G823": 3574.22,
        "A1Q874": 1099.98,
        "APC840": 1630.46
      },
      "por_almacen": {
        "ABARROTES": 81296.89,
        "REFRIGERADOS": 16625.32
      },
      "por_estado": {
        "Picking_Regular": 71276.79,
        "Picking Directo": 26645.42
      },
      "total_kg": 97922.21,
      "total_registros": 5343
    },
    "2026-06-27": {
      "por_familia": {
        "A": 31042.76,
        "B": 24273.76,
        "C": 21484.44,
        "F": 6529.69,
        "G": 582.2,
        "D": 3337.03,
        "E": 10720.77
      },
      "por_status": {
        "A": 19946.08,
        "C": 18726.2,
        "P": 16162.95,
        "B": 17668.27,
        "D": 25467.15
      },
      "por_placa": {
        "F7X829": 1812.25,
        "AWH909": 2950.25,
        "A5Y854": 2306.4,
        "AUP711": 2003.3,
        "ASM907": 1974.94,
        "F1E927": 3397.82,
        "APU790": 1146.14,
        "AXH708": 2442.56,
        "BBI909": 1282.18,
        "AXB855": 2073.28,
        "A6P899": 1798.49,
        "A5K897": 1084.55,
        "A7Y808": 1512.53,
        "P4A742": 2240.43,
        "C1J747": 2089.57,
        "C8F736": 1286.41,
        "D1V932": 2133.3,
        "B0V924": 1171.83,
        "BKV855": 2362.69,
        "ASM812": 1584.01,
        "C5G823": 2269.54,
        "T6F869": 1462.37,
        "D3L703": 3007.44,
        "F3M892": 1998.9,
        "A4G840": 2021.55,
        "APC840": 2525.3,
        "ARZ862": 1434.08,
        "A6R946": 2241.21,
        "AHX902": 1976.39,
        "CKI862": 1398.32,
        "ATB831": 1776.09,
        "D9G880": 2082.38,
        "ANI940": 2087.64,
        "F9W785": 2216.27,
        "D0I718": 1374.66,
        "V2F841": 1273.5,
        "ARD784": 2247.73,
        "ATP870": 1794.67,
        "AMQ791": 1399.35,
        "D4R705": 2426.85,
        "C3Q769": 1356.2,
        "C2B801": 1629.7,
        "F7B746": 1855.72,
        "APB825": 1712.86,
        "A1Q874": 1392.17,
        "AWC785": 1308.94,
        "AMF737": 3117.73,
        "D7L941": 2404.35,
        "W6L701": 2233.33,
        "C5R934": 3292.5
      },
      "por_almacen": {
        "ABARROTES": 80743.33,
        "REFRIGERADOS": 17227.33
      },
      "por_estado": {
        "Picking_Regular": 67048.45,
        "Picking Directo": 30922.2
      },
      "total_kg": 97970.65,
      "total_registros": 5006
    },
    "2026-06-29": {
      "por_familia": {
        "A": 33042.49,
        "B": 23021.17,
        "C": 21224.58,
        "F": 5653.28,
        "G": 305.98,
        "E": 10966.32,
        "D": 3125.64
      },
      "por_status": {
        "C": 21341.95,
        "B": 23756.08,
        "A": 16961.24,
        "P": 9332.71,
        "D": 25947.49
      },
      "por_placa": {
        "APC840": 2050.84,
        "C8F736": 1293.18,
        "W6L701": 1720.57,
        "ATB831": 1596.32,
        "C5G823": 2811.88,
        "A4G840": 1779.85,
        "D3L703": 3003.54,
        "P4A742": 3874.6,
        "C5R934": 2247.32,
        "APU790": 1648.34,
        "AMQ791": 2188.26,
        "D0I718": 1199.96,
        "D2H719": 2218.39,
        "F7X829": 1308.85,
        "A5K897": 1492.49,
        "ASM812": 2031.16,
        "AMF737": 1253.78,
        "AWC785": 2018.76,
        "ASA790": 1867.85,
        "D9G880": 1646.97,
        "T6F869": 1238.4,
        "APB825": 2978.88,
        "D7L941": 1878.81,
        "F7B746": 1742.68,
        "C3Q769": 1455.16,
        "A6P899": 1115.74,
        "C2B801": 1253.51,
        "AXB855": 1626.72,
        "C1J747": 2283.41,
        "A6R946": 1520.78,
        "AHX902": 2226.19,
        "D4R705": 1362.24,
        "CKI862": 1342.57,
        "AUP711": 3428.93,
        "F9W785": 2077.09,
        "AXH708": 3260.17,
        "ACX716": 1796.15,
        "BKV855": 1195.95,
        "ARZ862": 1351.75,
        "A1Q874": 2410.81,
        "V2F841": 2163.54,
        "D1V932": 2278.52,
        "A5Y854": 2895.08,
        "ANI940": 1699.27,
        "B0V924": 1141.85,
        "F1E927": 2582.95,
        "ARD784": 1443.93,
        "A7Y808": 1447.6,
        "ASM907": 1569.57,
        "BBI909": 1469.84,
        "ATP870": 1848.49
      },
      "por_almacen": {
        "ABARROTES": 80725.86,
        "REFRIGERADOS": 16613.6
      },
      "por_estado": {
        "Picking_Regular": 67059.83,
        "Picking Directo": 30279.64
      },
      "total_kg": 97339.46,
      "total_registros": 5120
    },
    "2026-06-30": {
      "por_familia": {
        "A": 24797.03,
        "B": 23238.26,
        "C": 19952.17,
        "F": 5944.76,
        "E": 10426.76,
        "D": 3854.69,
        "G": 500.19
      },
      "por_status": {
        "B": 19749.57,
        "A": 15231.12,
        "P": 11534.29,
        "D": 25902.99,
        "C": 16295.88
      },
      "por_placa": {
        "F1E927": 1637.37,
        "APB825": 1573.03,
        "C3Q769": 1211.88,
        "A5K897": 2062.42,
        "ATP870": 1149.08,
        "D9G880": 1761.47,
        "ASM907": 1217.77,
        "ASM812": 1177.9,
        "APC840": 1239.43,
        "ATB831": 1856.16,
        "D0I718": 1283.11,
        "A7Y808": 1968.49,
        "ARZ862": 2039.91,
        "AMQ791": 2666.11,
        "F3M892": 1870.37,
        "ARD784": 1532.1,
        "F9W785": 1485.6,
        "BBI909": 3447.53,
        "C5G823": 1166.16,
        "BKV855": 1028.69,
        "AXB855": 1402.05,
        "C5R934": 1332.83,
        "D1V932": 1844.21,
        "C8F736": 2083.99,
        "A4G840": 1984.44,
        "F7X829": 1432.03,
        "AWH909": 1435.06,
        "F7B746": 2003.55,
        "AXH708": 1972.85,
        "APU790": 1755.56,
        "D7L941": 1401.36,
        "AMF737": 1449.85,
        "CKI862": 1406.63,
        "D3L703": 1119.45,
        "V2F841": 3027.82,
        "W6L701": 1425.3,
        "AUP711": 1995.4,
        "ASA790": 1707.13,
        "P4A742": 2956.25,
        "ANI940": 1639.56,
        "A1Q874": 1653.27,
        "C2B801": 3581.61,
        "A6P899": 1428.75,
        "D4R705": 1609.59,
        "C1J747": 1027.33,
        "AHX902": 1649.88,
        "T6F869": 1869.32,
        "AWC785": 1179.71,
        "D2H719": 1483.88,
        "A5Y854": 1138.04,
        "ACX716": 1537.42,
        "A6R946": 1805.16
      },
      "por_almacen": {
        "ABARROTES": 72375.77,
        "REFRIGERADOS": 16338.09
      },
      "por_estado": {
        "Picking_Regular": 61777.72,
        "Picking Directo": 26936.14
      },
      "total_kg": 88713.86,
      "total_registros": 5296
    }
  }
}